README.rst
repograph.py
setup.py
repograph.egg-info/PKG-INFO
repograph.egg-info/SOURCES.txt
repograph.egg-info/dependency_links.txt
repograph.egg-info/entry_points.txt
repograph.egg-info/requires.txt
repograph.egg-info/top_level.txt